langchain_azure_postgresql/__init__.py
langchain_azure_postgresql/common/__init__.py
langchain_azure_postgresql/common/_connection.py
langchain_azure_postgresql/common/_shared.py
langchain_azure_postgresql/common/aio/__init__.py
langchain_azure_postgresql/common/aio/_connection.py
langchain_azure_postgresql/langchain/__init__.py
langchain_azure_postgresql/langchain/_shared.py
langchain_azure_postgresql/langchain/_vectorstore.py
langchain_azure_postgresql/langchain/aio/__init__.py
langchain_azure_postgresql/langchain/aio/_vectorstore.py
langchain_azure_postgresql/py.typed
langchain_azure_postgresql-0.3.0.dist-info/WHEEL
langchain_azure_postgresql-0.3.0.dist-info/METADATA
langchain_azure_postgresql-0.3.0.dist-info/RECORD
