Metadata-Version: 2.3
Name: langchain-azure-postgresql
Version: 0.3.0
Summary: LangChain VectorStore integrations for Azure Database for PostgreSQL
Keywords: azure,postgresql,langchain,vectorstore,database
Author: Arda Aytekin
Author-email: Arda Aytekin <8845951+aytekinar@users.noreply.github.com>
License: MIT License
Classifier: Development Status :: 5 - Production/Stable
Classifier: Framework :: AsyncIO
Classifier: Framework :: Pydantic :: 2
Classifier: Framework :: tox
Classifier: Intended Audience :: Developers
Classifier: Intended Audience :: End Users/Desktop
Classifier: License :: OSI Approved :: MIT License
Classifier: Programming Language :: Python :: 3.10
Classifier: Programming Language :: Python :: 3.11
Classifier: Programming Language :: Python :: 3.12
Classifier: Programming Language :: Python :: 3.13
Classifier: Topic :: Database
Classifier: Topic :: Scientific/Engineering :: Artificial Intelligence
Classifier: Topic :: Text Processing
Requires-Dist: aiohttp~=3.0
Requires-Dist: azure-identity~=1.0
Requires-Dist: langchain-core~=0.3.0
Requires-Dist: numpy~=2.0
Requires-Dist: pgvector~=0.4.0
Requires-Dist: psycopg[binary,pool]~=3.0
Requires-Dist: pydantic~=2.0
Requires-Dist: simsimd~=6.0
Requires-Dist: typing-extensions~=4.0 ; python_full_version < '3.12'
Maintainer: Arda Aytekin, Orhan Kislal
Maintainer-email: Arda Aytekin <8845951+aytekinar@users.noreply.github.com>, Orhan Kislal <kislalorhan@microsoft.com>
Requires-Python: ~=3.10
Project-URL: Release Notes, https://github.com/langchain-ai/langchain-azure/releases
Project-URL: Source Code, https://github.com/langchain-ai/langchain-azure/tree/main/libs/azure-postgresql
Project-URL: repository, https://github.com/langchain-ai/langchain-azure
